{
  "url": "https://logistics-next.netlify.app/",
  "requestedUrl": "https://logistics-next.netlify.app/",
  "timestamp": 1627951531612,
  "ranks": {
    "hundos": 2,
    "performance": 3,
    "accessibility": 2,
    "cumulative": 2
  },
  "lighthouse": {
    "version": "6.5.0",
    "performance": 0.68,
    "accessibility": 0.98,
    "bestPractices": 0.93,
    "seo": 1,
    "total": 359
  },
  "firstContentfulPaint": 1985.1409999999996,
  "speedIndex": 6925.793534000002,
  "largestContentfulPaint": 5717.095499999999,
  "totalBlockingTime": 22.081999999999994,
  "cumulativeLayoutShift": 0.03608970642089843,
  "timeToInteractive": 2014.1389999999997,
  "maxPotentialFirstInputDelay": 202.99999999999977,
  "timeToFirstByte": 7.264000000000003,
  "weight": {
    "summary": "26 requests • 2,815 KiB",
    "total": 2882255,
    "image": 2740618,
    "imageCount": 7,
    "script": 84921,
    "scriptCount": 10,
    "document": 9764,
    "font": 40327,
    "fontCount": 5,
    "stylesheet": 6625,
    "stylesheetCount": 2,
    "thirdParty": 41443,
    "thirdPartyCount": 6
  },
  "run": {
    "number": 3,
    "total": 3
  },
  "axe": {
    "passes": 500,
    "violations": 40
  }
}