{
  "url": "https://web3templates.com/",
  "requestedUrl": "https://web3templates.com/",
  "timestamp": 1658368935280,
  "ranks": {
    "hundos": 5,
    "performance": 4,
    "accessibility": 5,
    "cumulative": 5
  },
  "lighthouse": {
    "version": "6.5.0",
    "performance": 0.94,
    "accessibility": 0.9,
    "bestPractices": 0.93,
    "seo": 0.92,
    "total": 369
  },
  "firstContentfulPaint": 1705.1670000000001,
  "speedIndex": 1705.1670000000001,
  "largestContentfulPaint": 2146.4770000000003,
  "totalBlockingTime": 281.5159999999996,
  "cumulativeLayoutShift": 0.05761260986328125,
  "timeToInteractive": 4525.769,
  "maxPotentialFirstInputDelay": 423,
  "timeToFirstByte": 52.43000000000001,
  "weight": {
    "summary": "34 requests • 357 KiB",
    "total": 365445,
    "image": 2226,
    "imageCount": 4,
    "script": 281753,
    "scriptCount": 20,
    "document": 14782,
    "font": 38425,
    "fontCount": 1,
    "stylesheet": 13908,
    "stylesheetCount": 2,
    "thirdParty": 43133,
    "thirdPartyCount": 8
  },
  "run": {
    "number": 1,
    "total": 1
  },
  "axe": {
    "passes": 225,
    "violations": 18
  }
}