{
  "url": "https://web3templates.com/components",
  "requestedUrl": "https://web3templates.com/components",
  "timestamp": 1665541880392,
  "ranks": {
    "hundos": 4,
    "performance": 4,
    "accessibility": 4,
    "cumulative": 4
  },
  "lighthouse": {
    "version": "6.5.0",
    "performance": 0.82,
    "accessibility": 0.9,
    "bestPractices": 0.93,
    "seo": 0.92,
    "total": 357
  },
  "firstContentfulPaint": 1838.0590000000004,
  "speedIndex": 1838.0590000000004,
  "largestContentfulPaint": 3056.533,
  "totalBlockingTime": 529.3470000000002,
  "cumulativeLayoutShift": 0.06487400902642143,
  "timeToInteractive": 3700.0755000000004,
  "maxPotentialFirstInputDelay": 494,
  "timeToFirstByte": 8.293,
  "weight": {
    "summary": "36 requests • 343 KiB",
    "total": 351663,
    "image": 750,
    "imageCount": 1,
    "script": 162573,
    "scriptCount": 21,
    "document": 4031,
    "font": 38424,
    "fontCount": 1,
    "stylesheet": 14322,
    "stylesheetCount": 2,
    "thirdParty": 41715,
    "thirdPartyCount": 5
  },
  "run": {
    "number": 1,
    "total": 1
  },
  "axe": {
    "passes": 226,
    "violations": 12
  }
}