{
  "url": "https://web3canvas.com/",
  "requestedUrl": "https://web3canvas.com/",
  "timestamp": 1628037443133,
  "ranks": {
    "hundos": 6,
    "performance": 6,
    "accessibility": 6,
    "cumulative": 6
  },
  "lighthouse": {
    "version": "6.5.0",
    "performance": 0.17,
    "accessibility": 0.67,
    "bestPractices": 0.93,
    "seo": 0.84,
    "total": 261
  },
  "firstContentfulPaint": 5117.105000000001,
  "speedIndex": 7455.702195503546,
  "largestContentfulPaint": 6548.765000000001,
  "totalBlockingTime": 2357.2729977417002,
  "cumulativeLayoutShift": 0.011592641406589084,
  "timeToInteractive": 13965.076,
  "maxPotentialFirstInputDelay": 619.0000000000009,
  "timeToFirstByte": 368.011,
  "weight": {
    "summary": "111 requests • 1,988 KiB",
    "total": 2035686,
    "image": 512063,
    "imageCount": 15,
    "script": 631822,
    "scriptCount": 45,
    "document": 45322,
    "font": 157180,
    "fontCount": 6,
    "stylesheet": 671808,
    "stylesheetCount": 36,
    "thirdParty": 376016,
    "thirdPartyCount": 31
  },
  "run": {
    "number": 3,
    "total": 3
  },
  "axe": {
    "passes": 1133,
    "violations": 193
  }
}