{
  "url": "https://web3canvas.com/",
  "requestedUrl": "https://web3canvas.com/",
  "timestamp": 1661566768013,
  "ranks": {
    "hundos": 6,
    "performance": 6,
    "accessibility": 6,
    "cumulative": 6
  },
  "lighthouse": {
    "version": "6.5.0",
    "performance": 0.07,
    "accessibility": 0.67,
    "bestPractices": 0.93,
    "seo": 0.84,
    "total": 251
  },
  "firstContentfulPaint": 5724.359000000002,
  "speedIndex": 9241.418693116322,
  "largestContentfulPaint": 10091.679000000004,
  "totalBlockingTime": 1748.8864302368138,
  "cumulativeLayoutShift": 1.496212000846863,
  "timeToInteractive": 14422.218715118412,
  "maxPotentialFirstInputDelay": 738,
  "timeToFirstByte": 531.973,
  "weight": {
    "summary": "125 requests • 2,193 KiB",
    "total": 2245777,
    "image": 646349,
    "imageCount": 21,
    "script": 662776,
    "scriptCount": 50,
    "document": 48455,
    "font": 192610,
    "fontCount": 9,
    "stylesheet": 675356,
    "stylesheetCount": 35,
    "thirdParty": 540383,
    "thirdPartyCount": 46
  },
  "run": {
    "number": 1,
    "total": 1
  },
  "axe": {
    "passes": 1106,
    "violations": 154
  }
}