{
  "url": "https://logistics-next.vercel.app/",
  "requestedUrl": "https://logistics-next.vercel.app/",
  "timestamp": 1664935776065,
  "ranks": {
    "hundos": 6,
    "performance": 6,
    "accessibility": 3,
    "cumulative": 6
  },
  "lighthouse": {
    "version": "6.5.0",
    "performance": 0.77,
    "accessibility": 0.98,
    "bestPractices": 0.87,
    "seo": 1,
    "total": 362
  },
  "firstContentfulPaint": 1891.5990000000002,
  "speedIndex": 2787.4646859999993,
  "largestContentfulPaint": 5967.276500000001,
  "totalBlockingTime": 46,
  "cumulativeLayoutShift": 0.03669166564941406,
  "timeToInteractive": 2204.099,
  "maxPotentialFirstInputDelay": 118,
  "timeToFirstByte": 84.876,
  "weight": {
    "summary": "26 requests • 1,389 KiB",
    "total": 1422523,
    "image": 1270102,
    "imageCount": 7,
    "script": 94060,
    "scriptCount": 10,
    "document": 10335,
    "font": 40480,
    "fontCount": 5,
    "stylesheet": 7546,
    "stylesheetCount": 2,
    "thirdParty": 41613,
    "thirdPartyCount": 6
  },
  "run": {
    "number": 1,
    "total": 1
  },
  "axe": {
    "passes": 500,
    "violations": 39
  }
}