{
  "url": "https://mission-control.app/",
  "requestedUrl": "https://mission-control.app/",
  "timestamp": 1622163955263,
  "ranks": {
    "hundos": 1,
    "performance": 4,
    "accessibility": 1,
    "cumulative": 1
  },
  "lighthouse": {
    "version": "6.5.0",
    "performance": 0.98,
    "accessibility": 1,
    "bestPractices": 1,
    "seo": 1,
    "total": 398
  },
  "firstContentfulPaint": 2030.2230000000002,
  "speedIndex": 2030.2230000000002,
  "largestContentfulPaint": 2181.7400000000002,
  "totalBlockingTime": 10,
  "cumulativeLayoutShift": 0.025569064670138888,
  "timeToInteractive": 2441.5155000000004,
  "maxPotentialFirstInputDelay": 65,
  "timeToFirstByte": 39.536,
  "weight": {
    "summary": "25 requests • 254 KiB",
    "total": 259929,
    "image": 71652,
    "imageCount": 3,
    "script": 117293,
    "scriptCount": 11,
    "document": 7396,
    "font": 55414,
    "fontCount": 2,
    "stylesheet": 5303,
    "stylesheetCount": 2,
    "thirdParty": 107636,
    "thirdPartyCount": 7
  },
  "run": {
    "number": 3,
    "total": 3
  },
  "axe": {
    "passes": 298,
    "violations": 24
  }
}