{
  "url": "https://mission-control.app/",
  "requestedUrl": "https://mission-control.app/",
  "timestamp": 1630715900844,
  "ranks": {
    "hundos": 1,
    "performance": 4,
    "accessibility": 1,
    "cumulative": 1
  },
  "lighthouse": {
    "version": "6.5.0",
    "performance": 0.97,
    "accessibility": 1,
    "bestPractices": 1,
    "seo": 1,
    "total": 397
  },
  "firstContentfulPaint": 2028.4849999999997,
  "speedIndex": 2028.4849999999997,
  "largestContentfulPaint": 2253.8224999999993,
  "totalBlockingTime": 28,
  "cumulativeLayoutShift": 0.02536127387152778,
  "timeToInteractive": 2660.2725,
  "maxPotentialFirstInputDelay": 75,
  "timeToFirstByte": 153.467,
  "weight": {
    "summary": "25 requests • 254 KiB",
    "total": 260100,
    "image": 71692,
    "imageCount": 3,
    "script": 117324,
    "scriptCount": 11,
    "document": 7397,
    "font": 55545,
    "fontCount": 2,
    "stylesheet": 5295,
    "stylesheetCount": 2,
    "thirdParty": 107778,
    "thirdPartyCount": 7
  },
  "run": {
    "number": 2,
    "total": 3
  },
  "axe": {
    "passes": 298,
    "violations": 24
  }
}