{
  "url": "https://surjithctly.in/",
  "requestedUrl": "https://surjithctly.in/",
  "timestamp": 1625359054920,
  "ranks": {
    "hundos": 3,
    "performance": 1,
    "accessibility": 3,
    "cumulative": 3
  },
  "lighthouse": {
    "version": "6.5.0",
    "performance": 1,
    "accessibility": 0.95,
    "bestPractices": 0.93,
    "seo": 0.92,
    "total": 380
  },
  "firstContentfulPaint": 834.827,
  "speedIndex": 834.827,
  "largestContentfulPaint": 834.827,
  "totalBlockingTime": 6.5,
  "cumulativeLayoutShift": 0.05577573140462239,
  "timeToInteractive": 913.327,
  "maxPotentialFirstInputDelay": 84,
  "timeToFirstByte": 78.53399999999999,
  "weight": {
    "summary": "5 requests • 41 KiB",
    "total": 42155,
    "image": 34593,
    "imageCount": 1,
    "script": 1645,
    "scriptCount": 1,
    "document": 5790,
    "font": 0,
    "fontCount": 0,
    "stylesheet": 0,
    "stylesheetCount": 0,
    "thirdParty": 1772,
    "thirdPartyCount": 3
  },
  "run": {
    "number": 2,
    "total": 3
  },
  "axe": {
    "passes": 149,
    "violations": 8
  }
}